mpbn/__init__.py
mpbn/converters.py
mpbn/simulation.py
mpbn/asplib/eval_circuit.asp
mpbn/asplib/eval_mixed.asp
mpbn/asplib/mp_attractor.asp
mpbn/asplib/mp_eval.asp
mpbn/asplib/mp_positivereach-np.asp
mpbn/boolfunclib/__init__.py
mpbn/boolfunclib/aeon_impl.py
mpbn/boolfunclib/pyeda_impl.py
mpbn/cli/__init__.py
mpbn/cli/sim.py
tests/__init__.py
tests/test_attractors.py
tests/test_dynamics.py
tests/test_fixpoints.py
tests/test_input.py
tests/test_reachability.py
tests/test_reachable_attractors.py
mpbn-4.2.dist-info/METADATA
mpbn-4.2.dist-info/WHEEL
mpbn-4.2.dist-info/entry_points.txt
mpbn-4.2.dist-info/top_level.txt
mpbn-4.2.dist-info/RECORD
