Metadata-Version: 2.4
Name: mpbn
Version: 4.2
Summary: Simple implementation of Most Permissive Boolean networks
Home-page: https://github.com/bnediction/mpbn
Author: Loïc Paulevé
Author-email: loic.pauleve@labri.fr
License: CeCILL
Classifier: Intended Audience :: Science/Research
Classifier: Topic :: Scientific/Engineering
Classifier: Topic :: Scientific/Engineering :: Artificial Intelligence
Classifier: Topic :: Scientific/Engineering :: Bio-Informatics
Requires-Dist: boolean.py
Requires-Dist: clingo
Requires-Dist: colomoto_jupyter>=0.8.0
Requires-Dist: numpy
Requires-Dist: biodivine_aeon>=1.0.1
Requires-Dist: scipy
Requires-Dist: tqdm
Dynamic: author
Dynamic: author-email
Dynamic: classifier
Dynamic: description
Dynamic: description-content-type
Dynamic: home-page
Dynamic: keywords
Dynamic: license
Dynamic: requires-dist
Dynamic: summary
